pydoge/__init__.py
pydoge/config.py
pydoge/connection_dbcursor.py
pydoge/http_service.py
pydoge/logger.py
pydoge/timestamp.py
pydoge/utils.py
PyDoge-0.1.7.dist-info/LICENSE
PyDoge-0.1.7.dist-info/METADATA
PyDoge-0.1.7.dist-info/WHEEL
PyDoge-0.1.7.dist-info/top_level.txt
PyDoge-0.1.7.dist-info/RECORD
